jack_midi_split/__init__.py
jack_midi_split-1.0.1.dist-info/LICENSE
jack_midi_split-1.0.1.dist-info/WHEEL
jack_midi_split-1.0.1.dist-info/METADATA
jack_midi_split-1.0.1.dist-info/RECORD
