Metadata-Version: 2.1
Name: jack_midi_split
Version: 1.0.1
Summary: Provides a jack client which can be instructed to split noteon/noteoff events
Author-email: Leon Dionne <ldionne@dridesign.sh.cn>
Classifier: License :: OSI Approved :: GNU General Public License v3 or later (GPLv3+)
Classifier: Programming Language :: Python
Classifier: Programming Language :: Python :: 3.10
Classifier: Topic :: Multimedia :: Sound/Audio :: Sound Synthesis
Classifier: Topic :: Multimedia :: Sound/Audio :: MIDI
Requires-Dist: JACK-Client
Project-URL: Home, https://github.com/Zen-Master-SoSo/jack_midi_split
